# 概览

* enum关键字在 java5 中引入，表示一种特殊类型的类
* 枚举类是一种“语法糖”，**只有编译器知道“enum”关键字，jvm是不知道的，字节码文件中没有枚举这一概念**
* 其总是继承java.lang.Enum类，所以不能枚举不能继承其他类，但是可以实现接口
* 枚举构造函数默认是私有的



# 自定义枚举方法

**可以在枚举的外面定义一个 类，用来实现关于枚举的各个API**

```java
public class Pizza {
    private PizzaStatus status;
    public enum PizzaStatus {
        ORDERED,
        READY,
        DELIVERED;
    }
 
    public boolean isDeliverable() {
        if (getStatus() == PizzaStatus.READY) {
            returntrue;
        }
        returnfalse;
    }
     
    // Methods that set and get the status variable.
}	
```

# 在switch语句中使用枚举类型

```java
public int getDeliveryTimeInDays() {
    switch (status) {
        case ORDERED: return5;
        case READY: return2;
        case DELIVERED: return0;
    }
    return0;
}
```



# 在枚举中定义方法

```java
publicclass Pizza {
 
    private PizzaStatus status;
    public enum PizzaStatus {
        ORDERED (5){
            @Override
            public boolean isOrdered() {
                returntrue;
            }
        },
        READY (2){
            @Override
            public boolean isReady() {
                returntrue;
            }
        },
        DELIVERED (0){
            @Override
            public boolean isDelivered() {
                returntrue;
            }
        };
 
        private int timeToDelivery;
 
        public boolean isOrdered() {returnfalse;}
 
        public boolean isReady() {returnfalse;}
 
        public boolean isDelivered(){returnfalse;}
 
        public int getTimeToDelivery() {
            return timeToDelivery;
        }
 
        PizzaStatus (int timeToDelivery) {
            this.timeToDelivery = timeToDelivery;
        }
    }
 
    public boolean isDeliverable() {
        returnthis.status.isReady();
    }
 
    public void printTimeToDeliver() {
        System.out.println("Time to delivery is " +
          this.getStatus().getTimeToDelivery());
    }
     
    // Methods that set and get the status variable.
}
```



# 枚举反编译

## 原始代码

```java
public enum Fruit {
    APPLE, BANANA, WATERMELON;
    private int value;

    private Fruit() {
        //默认构造器
        this.value = 0;
    }

    private Fruit(int value) {
        //带参数的构造器
        this.value = value;
    }
}
```





## JVM字节码

> 简单反编译：javap -p DateTypeEnum.class
>
> 复杂编译：javap -c DateTypeEnum

```java
public final class Fruit extends java.lang.Enum<Fruit> {
  public static final Fruit APPLE;

  public static final Fruit BANANA;

  public static final Fruit WATERMELON;

  public static Fruit[] values();
    Code:
       0: getstatic     #1                  // Field $VALUES:[LFruit;
       3: invokevirtual #2                  // Method "[LFruit;".clone:()Ljava/lang/Object;
       6: checkcast     #3                  // class "[LFruit;"
       9: areturn

  public static Fruit valueOf(java.lang.String);
    Code:
       0: ldc           #4                  // class Fruit
       2: aload_0
       3: invokestatic  #5                  // Method java/lang/Enum.valueOf:(Ljava/lang/Class;Ljava/lang/String;)Ljava/lang/Enum;
       6: checkcast     #4                  // class Fruit
       9: areturn

  static {};
    Code:
       0: new           #4                  // class Fruit
       3: dup
       4: ldc           #8                  // String APPLE
       6: iconst_0
       7: invokespecial #9                  // Method "<init>":(Ljava/lang/String;I)V
      10: putstatic     #10                 // Field APPLE:LFruit;
      13: new           #4                  // class Fruit
      16: dup
      17: ldc           #11                 // String BANANA
      19: iconst_1
      20: invokespecial #9                  // Method "<init>":(Ljava/lang/String;I)V
      23: putstatic     #12                 // Field BANANA:LFruit;
      26: new           #4                  // class Fruit
      29: dup
      30: ldc           #13                 // String WATERMELON
      32: iconst_2
      33: invokespecial #9                  // Method "<init>":(Ljava/lang/String;I)V
      36: putstatic     #14                 // Field WATERMELON:LFruit;
      39: iconst_3
      40: anewarray     #4                  // class Fruit
      43: dup
      44: iconst_0
      45: getstatic     #10                 // Field APPLE:LFruit;
      48: aastore
      49: dup
      50: iconst_1
      51: getstatic     #12                 // Field BANANA:LFruit;
      54: aastore
      55: dup
      56: iconst_2
      57: getstatic     #14                 // Field WATERMELON:LFruit;
      60: aastore
      61: putstatic     #1                  // Field $VALUES:[LFruit;
      64: return
}
```

## 最终源码

```java
public final class Fruit extends Enum {   
//3个枚举成员实例    
    public static final Fruit APPLE;    
    public static final Fruit BANANA;    
    public static final Fruit WATERMELON;    
    private int value;//普通变量    
    private static final Fruit ENUM$VALUES[];//存储枚举常量的枚举数组    
    static {
    //静态域，初始化枚举常量，枚举数组        
        APPLE = new Fruit("APPLE", 0);        
        BANANA = new Fruit("BANANA", 1);        
        WATERMELON = new Fruit("WATERMELON", 2);        
        ENUM$VALUES = (new Fruit[]{APPLE, BANANA, WATERMELON});    
    }
    private Fruit(String s, int i) {
        //编译器改造了默认构造器        
        super(s, i);        
        value = 0;    
    }    
    private Fruit(String s, int i, int value) {
        //编译器改造了带参数的构造器        
        super(s, i);        
        this.value = value;    
    }    
    public static Fruit[] values() {
        //编译器添加了静态方法values()        
        Fruit afruit[];        
        int i;        
        Fruit afruit1[];        
        System.arraycopy(afruit = ENUM$VALUES, 0, afruit1 = new Fruit[i = afruit.length], 0, i);        
        return afruit1;    
    }    
    public static Fruit valueOf(String s) {
        //编译器添加了静态方法valueOf()        
        return (Fruit) Enum.valueOf(Test_2018_1_16 / Fruit, s);    
    }
}
```

## 手动继承枚举

```java
public class MyEnum extends Enum { // 这样写肯定是通不过编译的，因为编译器不允许我们的类显示的继承Enum类

    private MyEnum() {}

    public static final MyEnum e1 = new MyEnum("WHITE", 0);
    public static final MyEnum e2 = new MyEnum("BLACK", 1);

    public MyEnum[] values() {
        return new MyEnum[]{e1, e2}; // 这个地方有问题，等下指出
    }
}
```





# 枚举可以定义抽象方法

**但是一定要在各自的示例中实现**

```
“不含抽象方法”的class反编译文件：public **final** class Weather extends Enum

“含有抽象方法”的class反编译文件：public **abstract**class Weather extends Enum
```

```java
public  enum Fruit {
    APPLE{
        @Override
        void doSomeThing() {
            
        }
    }, BANANA {
        @Override
        void doSomeThing() {
            
        }
    }, WATERMELON {
        @Override
        void doSomeThing() {
            
        }
    };
    private int value;

    Fruit() {
        //默认构造器
        this.value = 0;
    }

    Fruit(int value) {
        //带参数的构造器
        this.value = value;
    }

    abstract void doSomeThing();
}
```



# 进阶

## EnumSet

### 构造

**根据枚举类构造**

```java
EnumSet<Fruit> fruits = EnumSet.allOf(Fruit.class);
```

**根据枚举实例构造**

```java
EnumSet<Fruit> one = EnumSet.of(Fruit.APPLE);
EnumSet<Fruit> two = EnumSet.of(Fruit.APPLE,Fruit.BANANA);
EnumSet<Fruit> three = EnumSet.of(Fruit.APPLE,Fruit.BANANA,Fruit.WATERMELON);
```

**根据枚举集合的补集构造**

```java
EnumSet<Fruit> oneComp = EnumSet.complementOf(one);
```

**构造空枚举集合**

```java
EnumSet<Fruit> fruits1 = EnumSet.noneOf(Fruit.class);
EnumSet<Fruit> fruits2 = EnumSet.complementOf(fruits1);
```

**根据ordinary范围构造**

```java
EnumSet<Fruit> range = EnumSet.range(Fruit.APPLE, Fruit.WATERMELON);
```

### **使用**

**与一般的 Set集合 使用无异**







## EnumMap

* 会事先在内部初始化 一些key的集合，因此大小是固定的，性能比 *HashMap* 要好很多
* 会将 null值 映射成  为 *null object*

### 构造

```
EnumMap<Fruit,String> enumMap = new EnumMap<>(Fruit.class);
//此时出初始化了 指定枚举类型的key

enumMap.put(Fruit.APPLE,"xjq");
enumMap.put(Fruit.WATERMELON,null);
enumMap.put(Fruit.BANANA,"xjq");
```

**使用**

与普通*map* 使用无异

